docker_tui/__init__.py
docker_tui/cli.py
docker_tui/apis/__init__.py
docker_tui/apis/docker_api.py
docker_tui/apis/dockerhub_api.py
docker_tui/apis/models.py
docker_tui/services/__init__.py
docker_tui/services/container_filesystem_explorer.py
docker_tui/services/containers_stats_monitor.py
docker_tui/services/images_provider.py
docker_tui/utils/__init__.py
docker_tui/utils/async_background.py
docker_tui/utils/async_background_loop.py
docker_tui/utils/external_files_editor.py
docker_tui/utils/formating.py
docker_tui/utils/input_helpers.py
docker_tui/views/__init__.py
docker_tui/views/components/__init__.py
docker_tui/views/components/container_cpu_usage_plot.py
docker_tui/views/components/container_memory_usage_plot.py
docker_tui/views/components/containers_log.py
docker_tui/views/components/debounced_input_handler.py
docker_tui/views/components/dual_pane_container.py
docker_tui/views/components/header.py
docker_tui/views/components/responsive_table.py
docker_tui/views/components/shortcuts.py
docker_tui/views/components/system_details.py
docker_tui/views/components/time_series_plot.py
docker_tui/views/modals/__init__.py
docker_tui/views/modals/action_verification_modal.py
docker_tui/views/modals/dockerhub_search_modal.py
docker_tui/views/modals/menu_modal.py
docker_tui/views/modals/search_modal.py
docker_tui/views/pages/__init__.py
docker_tui/views/pages/container_details_page.py
docker_tui/views/pages/container_files_page.py
docker_tui/views/pages/container_log_page.py
docker_tui/views/pages/containers_list_page.py
docker_tui/views/pages/image_list_page.py
docker_tui/views/pages/page.py
docker_tui-0.1.7.dist-info/METADATA
docker_tui-0.1.7.dist-info/WHEEL
docker_tui-0.1.7.dist-info/entry_points.txt
docker_tui-0.1.7.dist-info/top_level.txt
docker_tui-0.1.7.dist-info/RECORD
