Metadata-Version: 2.4
Name: docker-tui
Version: 0.1.7
Summary: A console user interface for docker
Author: Assaf
License: MIT
Project-URL: Repository, https://github.com/asafc64/DockerTUI.git
Project-URL: Issues, https://github.com/asafc64/DockerTUI/issues
Requires-Python: >=3.10
